odoo/addons/report_qweb_parameter/README.rst
odoo/addons/report_qweb_parameter/__init__.py
odoo/addons/report_qweb_parameter/__manifest__.py
odoo/addons/report_qweb_parameter/demo/test_report_field_length.xml
odoo/addons/report_qweb_parameter/models/__init__.py
odoo/addons/report_qweb_parameter/models/ir_qweb.py
odoo/addons/report_qweb_parameter/static/description/icon.png
odoo/addons/report_qweb_parameter/tests/__init__.py
odoo/addons/report_qweb_parameter/tests/test_report_qweb_parameter.py
odoo11_addon_report_qweb_parameter-11.0.1.0.0.dist-info/DESCRIPTION.rst
odoo11_addon_report_qweb_parameter-11.0.1.0.0.dist-info/METADATA
odoo11_addon_report_qweb_parameter-11.0.1.0.0.dist-info/RECORD
odoo11_addon_report_qweb_parameter-11.0.1.0.0.dist-info/WHEEL
odoo11_addon_report_qweb_parameter-11.0.1.0.0.dist-info/metadata.json
odoo11_addon_report_qweb_parameter-11.0.1.0.0.dist-info/top_level.txt
